sample/__init__.py
sample/simple.py
taskuma2org-0.0.2.dist-info/METADATA
taskuma2org-0.0.2.dist-info/WHEEL
taskuma2org-0.0.2.dist-info/entry_points.txt
taskuma2org-0.0.2.dist-info/top_level.txt
taskuma2org-0.0.2.dist-info/RECORD
