Metadata-Version: 2.1
Name: taskuma2org
Version: 0.0.2
Summary: convert taskuma log to org file
Home-page: https://gitlab.com/antarcticafalls/taskuma2org
Author: antarcticafalls
Author-email: pxel8063@gmail.com
License: UNKNOWN
Project-URL: Bug Reports, https://gitlab.com/antarcticafalls/taskuma2org/issues
Project-URL: Source, https://gitlab.com/antarcticafalls/taskuma2org/
Platform: UNKNOWN
Classifier: Development Status :: 3 - Alpha
Classifier: Programming Language :: Python :: 3
Classifier: Programming Language :: Python :: 3.6
Classifier: Programming Language :: Python :: 3.7
Classifier: Programming Language :: Python :: 3.8
Classifier: Programming Language :: Python :: 3.9
Classifier: Programming Language :: Python :: 3 :: Only
Requires-Python: >=3.5, <4
Requires-Dist: memacs
Requires-Dist: click
Provides-Extra: dev
Requires-Dist: check-manifest ; extra == 'dev'
Provides-Extra: test
Requires-Dist: coverage ; extra == 'test'
